usr/lib/systemd/user/wiki_monkey.service
usr/lib/systemd/user/wiki_monkey@.service
usr/share/wiki-monkey/WikiMonkey-ArchWiki.js
usr/share/wiki-monkey/WikiMonkey-ArchWiki.min.js
usr/share/wiki-monkey/WikiMonkey-Wikipedia.js
usr/share/wiki-monkey/WikiMonkey-Wikipedia.min.js
wiki_monkey/__init__.py
wiki_monkey/aux.py
wiki_monkey/gencert.py
wiki_monkey/main.py
wiki_monkey/lib/__init__.py
wiki_monkey/lib/app.py
wiki_monkey/lib/static.py
wiki_monkey/lib/api/__init__.py
wiki_monkey/lib/api/bookmark.py
wiki_monkey/lib/api/maintenance.py
wiki_monkey/lib/models/__init__.py
wiki_monkey/lib/models/bookmark.py
wiki_monkey/migrations/README
wiki_monkey/migrations/alembic.ini
wiki_monkey/migrations/env.py
wiki_monkey/migrations/script.py.mako
wiki_monkey/migrations/__pycache__/env.cpython-310.pyc
wiki_monkey/migrations/__pycache__/env.cpython-37.pyc
wiki_monkey/migrations/__pycache__/env.cpython-38.pyc
wiki_monkey/migrations/__pycache__/env.cpython-39.pyc
wiki_monkey/migrations/versions/084293f15ed9_.py
wiki_monkey/migrations/versions/256c0764ec9b_.py
wiki_monkey/migrations/versions/8016da711d88_.py
wiki_monkey/migrations/versions/982a3822ee72_.py
wiki_monkey/migrations/versions/d88cb486ef0d_.py
wiki_snake/__init__.py
wiki_snake/aux.py
wiki_snake/gencert.py
wiki_snake/main.py
wiki_snake/lib/__init__.py
wiki_snake/lib/app.py
wiki_snake/lib/flask_rip.py
wiki_snake/lib/static.py
wiki_snake/lib/api/__init__.py
wiki_snake/lib/api/bookmark.py
wiki_snake/lib/api/maintenance.py
wiki_snake/lib/models/__init__.py
wiki_snake/lib/models/bookmark.py
wiki_snake/migrations/README
wiki_snake/migrations/alembic.ini
wiki_snake/migrations/env.py
wiki_snake/migrations/script.py.mako
wiki_snake/migrations/__pycache__/env.cpython-37.pyc
wiki_snake/migrations/versions/084293f15ed9_.py
wiki_snake/migrations/versions/256c0764ec9b_.py
wiki_snake/migrations/versions/8016da711d88_.py
wiki_snake/migrations/versions/982a3822ee72_.py
wiki_snake/migrations/versions/d88cb486ef0d_.py
wiki_monkey-5.5.3.dist-info/LICENSE
wiki_monkey-5.5.3.dist-info/METADATA
wiki_monkey-5.5.3.dist-info/WHEEL
wiki_monkey-5.5.3.dist-info/entry_points.txt
wiki_monkey-5.5.3.dist-info/top_level.txt
wiki_monkey-5.5.3.dist-info/RECORD
